multiplied/.python-version
multiplied/__init__.py
multiplied/analysis/__init__.py
multiplied/analysis/extract.py
multiplied/analysis/search.py
multiplied/analysis/track.py
multiplied/core/__init__.py
multiplied/core/algorithm.py
multiplied/core/map.py
multiplied/core/matrix.py
multiplied/core/template.py
multiplied/core/templates/__init__.py
multiplied/core/templates/adder.py
multiplied/core/templates/csa.py
multiplied/core/templates/decoder.py
multiplied/core/truth.py
multiplied/core/utils/__init__.py
multiplied/core/utils/char.py
multiplied/core/utils/pretty.py
multiplied/datasets/__init__.py
multiplied/datasets/default.parquet
multiplied/io/__init__.py
multiplied/io/_db.py
multiplied/io/lazy_json.py
multiplied/io/parquet.py
multiplied/tests/__init__.py
multiplied/tests/test_algorithm.py
multiplied/tests/test_maps.py
multiplied/tests/test_population.py
multiplied/tests/test_templates.py
multiplied/tests/test_to_json.py
multiplied/tests/test_truth.py
multiplied/tests/test_utils.py
multiplied-0.3.3.dist-info/licenses/LICENSE
multiplied-0.3.3.dist-info/WHEEL
multiplied-0.3.3.dist-info/METADATA
multiplied-0.3.3.dist-info/RECORD
