Metadata-Version: 2.4
Name: multiplied
Version: 0.3.3
Summary: A powerful tool to build, test, and analyse multiplier designs.
License-Expression: AGPL-3.0-or-later
License-File: LICENSE
Requires-Dist: toml>=0.10.2
Requires-Python: >=3.13
Project-URL: Homepage, https://github.com/EphraimCompEng/multiplied
Project-URL: Issues, https://github.com/EphraimCompEng/multiplied/issues
